devtools_border_radius/__init__.py
devtools_border_radius-1.0.1.dist-info/METADATA
devtools_border_radius-1.0.1.dist-info/WHEEL
devtools_border_radius-1.0.1.dist-info/top_level.txt
devtools_border_radius-1.0.1.dist-info/RECORD
