Metadata-Version: 2.1
Name: devtools-border-radius
Version: 1.0.1
Summary: CSS border-radius generator
Home-page: https://devtools.at/tools/border-radius
Author: DevTools.at
Author-email: hello@devtools.at
Project-URL: Homepage, https://devtools.at/tools/border-radius
Project-URL: Repository, https://github.com/devtools-at/border-radius
Classifier: Development Status :: 4 - Beta
Classifier: Intended Audience :: Developers
Classifier: License :: OSI Approved :: MIT License
Classifier: Programming Language :: Python :: 3
Requires-Python: >=3.8
